az_basics/__init__.py
az_basics/connection_string_based.py
az_basics/sas_token_based.py
az_basics/toy.py
az_basics-0.1.0.dist-info/METADATA
az_basics-0.1.0.dist-info/WHEEL
az_basics-0.1.0.dist-info/RECORD
